cactive_ip/__init__.py
cactive_ip-1.0.1.dist-info/METADATA
cactive_ip-1.0.1.dist-info/WHEEL
cactive_ip-1.0.1.dist-info/top_level.txt
cactive_ip-1.0.1.dist-info/RECORD
