Metadata-Version: 2.1
Name: cactive-ip
Version: 1.0.1
Summary: Swiftly retrieves data pertaining to an IP address.
Home-page: https://github.com/CactiveNetwork/ip-python
Author: Cactive
Author-email: legal@cactive.network
Project-URL: Bug Tracker, https://github.com/CactiveNetwork/ip-python/issues
Classifier: Programming Language :: Python :: 3
Classifier: License :: Other/Proprietary License
Classifier: Operating System :: OS Independent
Requires-Python: >=3.9
Requires-Dist: requests (==2.28.1)
